{
  "بيانات_الدرس": {
    "lecture_id": "a39d060c-8bc6-4b59-9160-c49f68c9f7fb",
    "عنوان_الدرس": "معرفة الله ـ عظمة الله ـ الدرس السابع",
    "رقم_الدرس": "7",
    "السلسلة": "معرفة الله",
    "نطاق_الآيات": "",
    "المتحدث": "حسين بدر الدين الحوثي",
    "التاريخ_الميلادي": "",
    "التاريخ_الهجري": "",
    "المكان": "اليمن ـ صعدة"
  },
  "الأقسام_الموضوعية": [
    {
      "رقم_القسم": 1,
      "اسم_القسم": "التمجيد والتعظيم وسيلة لترسيخ الثقة بالله",
      "ملخص_القسم": "يؤصّل الدرس لمنهجية تعزيز الثقة بالله عبر التمجيد والتعظيم من خلال آيات الثناء على كماله المطلق، مع التركيز على تكرار {لا إله إلا هو} كأداة لترسيخ الانشداد العاطفي والعملي نحو الله وحده.",
      "نطاق_الفقرات": {
        "البداية_sequence_index": 1,
        "النهاية_sequence_index": 19,
        "البداية_paragraph_id": "a4deace2-4e9d-4be0-adc1-8bcdf66418cb",
        "النهاية_paragraph_id": "d5c4ec64-d6a9-4612-9845-61618e9af771"
      },
      "الآيات_المرتبطة": [
        {"رقم_الاية": "22-24", "اسم_السورة": "الحشر"},
        {"رقم_الاية": "255", "اسم_السورة": "البقرة"},
        {"رقم_الاية": "65", "اسم_السورة": "غافر"},
        {"رقم_الاية": "18", "اسم_السورة": "الأنعام"},
        {"رقم_الاية": "70", "اسم_السورة": "القصص"},
        {"رقم_الاية": "73, 101-103", "اسم_السورة": "الأنعام"},
        {"رقم_الاية": "1-3", "اسم_السورة": "سبأ"},
        {"رقم_الاية": "1", "اسم_السورة": "التغابن"},
        {"رقم_الاية": "1", "اسم_السورة": "الحشر"},
        {"رقم_الاية": "83", "اسم_السورة": "يس"},
        {"رقم_الاية": "17-19", "اسم_السورة": "الروم"},
        {"رقم_الاية": "19", "اسم_السورة": "محمد"},
        {"رقم_الاية": "46", "اسم_السورة": "طه"},
        {"رقم_الاية": "217-220", "اسم_السورة": "الشعراء"}
      ],
      "concepts_tags": ["التمجيد", "التعظيم", "لا إله إلا الله", "الثقة بالله", "الانشداد العاطفي", "التوحيد العملي"]
    },
    {
      "رقم_القسم": 2,
      "اسم_القسم": "رحمة الله: المظهر الأعمق لكمال ألوهيته",
      "ملخص_القسم": "يستعرض الدرس تجليات رحمة الله في الخلق والتشريع والتدبير، مبيناً كيف أن تكرار اسم {الرحمن الرحيم} في القرآن يهدف لخلق شعور بالحياء والحب والخشية، مما يدفع المؤمن للشكر والعمل الصالح.",
      "نطاق_الفقرات": {
        "البداية_sequence_index": 20,
        "النهاية_sequence_index": 43,
        "البداية_paragraph_id": "d5c4ec64-d6a9-4612-9845-61618e9af771",
        "النهاية_paragraph_id": "f63b16e9-9d37-45ae-8c2f-421121d8a44c"
      },
      "الآيات_المرتبطة": [
        {"رقم_الاية": "15", "اسم_السورة": "محمد"},
        {"رقم_الاية": "70", "اسم_السورة": "الفرقان"},
        {"رقم_الاية": "114", "اسم_السورة": "هود"},
        {"رقم_الاية": "118", "اسم_السورة": "التوبة"},
        {"رقم_الاية": "261", "اسم_السورة": "البقرة"},
        {"رقم_الاية": "72", "اسم_السورة": "التوبة"},
        {"رقم_الاية": "2", "اسم_السورة": "الفاتحة"},
        {"رقم_الاية": "2", "اسم_السورة": "فصلت"}
      ],
      "concepts_tags": ["رحمة الله", "الشكر", "مضاعفة الأجر", "الحياء من الله", "التشريع الرحيم", "العلاقة الوجدانية"]
    },
    {
      "رقم_القسم": 3,
      "اسم_القسم": "الأسماء الحسنى: مفاتيح المعرفة والولاء",
      "ملخص_القسم": "يحلل الدرس دلالات الأسماء الإلهية في سورة الحشر (الملك، القدوس، السلام، المؤمن، المهيمن، العزيز، الجبار، المتكبر)، مبيناً كيف أن فهمها يخلق شعوراً بالعزة والطمأنينة ويرسخ الولاية لله وحده.",
      "نطاق_الفقرات": {
        "البداية_sequence_index": 44,
        "النهاية_sequence_index": 70,
        "البداية_paragraph_id": "461e724b-6724-46a8-8440-f66e4ad95a25",
        "النهاية_paragraph_id": "6f35cffd-9a87-4fef-a4c5-55628e27dff7"
      },
      "الآيات_المرتبطة": [
        {"رقم_الاية": "28", "اسم_السورة": "ابراهيم"},
        {"رقم_الاية": "34", "اسم_السورة": "ابراهيم"},
        {"رقم_الاية": "20", "اسم_السورة": "لقمان"},
        {"رقم_الاية": "17", "اسم_السورة": "عبس"},
        {"رقم_الاية": "22-23", "اسم_السورة": "الحشر"},
        {"رقم_الاية": "21", "اسم_السورة": "الحشر"},
        {"رقم_الاية": "1-3", "اسم_السورة": "الفاتحة"},
        {"رقم_الاية": "14", "اسم_السورة": "التوبة"},
        {"رقم_الاية": "35", "اسم_السورة": "محمد"}
      ],
      "concepts_tags": ["الأسماء الحسنى", "الملك القدوس", "السلام المؤمن", "المهيمن", "العزة الإلهية", "الولاية لله", "نقد الطواغيت"]
    },
    {
      "رقم_القسم": 4,
      "اسم_القسم": "الخالق البارئ المصور: شهادة الخلق بكمال الله",
      "ملخص_القسم": "يركز على أسماء الخالق والبارئ والمصور كدليل على إبداع الله وانفراده بالخلق، مستشهداً بقدرة الله على الإمداد بالمال والبنين، ومحذراً من الاغترار بالنعم دون شكر.",
      "نطاق_الفقرات": {
        "البداية_sequence_index": 71,
        "النهاية_sequence_index": 87,
        "البداية_paragraph_id": "4840fc36-694e-4f28-9cd0-b91e7ba19552",
        "النهاية_paragraph_id": "4645f374-f815-4b8d-92aa-5830e5628eaf"
      },
      "الآيات_المرتبطة": [
        {"رقم_الاية": "24", "اسم_السورة": "الحشر"},
        {"رقم_الاية": "6", "اسم_السورة": "الإسراء"},
        {"رقم_الاية": "10-12", "اسم_السورة": "نوح"},
        {"رقم_الاية": "255", "اسم_السورة": "البقرة"},
        {"رقم_الاية": "87", "اسم_السورة": "الزخرف"}
      ],
      "concepts_tags": ["الخلق والإبداع", "البارئ المصور", "الإمداد الإلهي", "شكر النعم", "عدم الاغترار", "التوكل على الخالق"]
    },
    {
      "رقم_القسم": 5,
      "اسم_القسم": "آية الكرسي والتسبيح: ترسيخ الشعور بالعظمة",
      "ملخص_القسم": "يستعرض آية الكرسي وآيات التسبيح كأدوات عملية لترسيخ استشعار عظمة الله في النفس، مع التأكيد على أن التسبيح والتهليل والتكبير عبادات ذات أثر وجداني عميق في معرفة الله.",
      "نطاق_الفقرات": {
        "البداية_sequence_index": 88,
        "النهاية_sequence_index": 95,
        "البداية_paragraph_id": "baa7934d-37cf-4cb2-b2d7-4731976fcb13",
        "النهاية_paragraph_id": "379cf87e-5b2c-472c-85f4-a561b2eab2be"
      },
      "الآيات_المرتبطة": [
        {"رقم_الاية": "255", "اسم_السورة": "البقرة"},
        {"رقم_الاية": "21", "اسم_السورة": "الحشر"}
      ],
      "concepts_tags": ["آية الكرسي", "التسبيح", "الذكر العملي", "استشعار العظمة", "العبادة الوجدانية", "أثر الأذكار"]
    },
    {
      "رقم_القسم": 6,
      "اسم_القسم": "نماذج تمجيد من أهل البيت: منهج عملي للمعرفة",
      "ملخص_القسم": "يقدم نماذج من أدعية الإمام زين العابدين في تمجيد الله كمثال عملي لكيفية ترسيخ المعرفة الواعية بالله، مع بيان أن هذه الأدعية تشد القلوب نحو الله وتعمق فهم أسمائه وصفاته.",
      "نطاق_الفقرات": {
        "البداية_sequence_index": 96,
        "النهاية_sequence_index": 101,
        "البداية_paragraph_id": "ff0735df-3467-4cb9-b9e1-16dffc5b5a48",
        "النهاية_paragraph_id": "6a6444df-e15a-43dd-afdb-37b33229d984"
      },
      "الآيات_المرتبطة": [],
      "concepts_tags": ["أدعية أهل البيت", "الإمام زين العابدين", "التمجيد العملي", "المعرفة الوجدانية", "دعاء يوم عرفة", "الخاتمة التطبيقية"]
    }
  ]
}