{
  "بيانات_الدرس": {
    "lecture_id": "5a2592a0-d6f2-4878-b8bb-f36d487985b8",
    "عنوان_الدرس": "معرفة الله ـ وعده ووعيده ـ الدرس العاشر",
    "رقم_الدرس": "10",
    "السلسلة": "معرفة الله",
    "نطاق_الآيات": "{رَبَّنَا أَرِنَا الَّذَيْنِ أَضَلاَّنَا مِنَ الْجِنِّ وَالإِنْسِ}",
    "المتحدث": "حسين بدر الدين الحوثي",
    "التاريخ_الميلادي": "",
    "التاريخ_الهجري": "16 ربيع الثاني",
    "المكان": "اليمن ـ صعدة"
  },
  "الأقسام_الموضوعية": [
    {
      "رقم_القسم": 1,
      "اسم_القسم": "تحول الصداقات الدنيوية إلى عداوة في الآخرة",
      "ملخص_القسم": "يبيّن القسم كيف تتحول العلاقات والصداقات القائمة على غير أساس صحيح في الدنيا إلى عداوة شديدة وحسرات في يوم القيامة، حيث يتبرأ الأتباع من المتبوعين والعكس.",
      "نطاق_الفقرات": {
        "البداية_sequence_index": 1,
        "النهاية_sequence_index": 17,
        "البداية_paragraph_id": "7fb8009f-8c72-455d-8d49-6cbbce2aa7d3",
        "النهاية_paragraph_id": "454de059-f9d1-4f60-b53f-1d07eb6d7f5f"
      },
      "الآيات_المرتبطة": [
        {"رقم_الاية": "66-67", "اسم_السورة": "الزخرف"},
        {"رقم_الاية": "18", "اسم_السورة": "الشعراء"},
        {"رقم_الاية": "38", "اسم_السورة": "الزخرف"},
        {"رقم_الاية": "29", "اسم_السورة": "فصلت"},
        {"رقم_الاية": "38", "اسم_السورة": "الأعراف"},
        {"رقم_الاية": "166-167", "اسم_السورة": "البقرة"},
        {"رقم_الاية": "22", "اسم_السورة": "إبراهيم"}
      ],
      "concepts_tags": ["الصداقة", "العداوة", "يوم القيامة", "الحسرة", "التبرؤ", "الأتباع", "المتبوعون"]
    },
    {
      "رقم_القسم": 2,
      "اسم_القسم": "الموقف الصحيح من قرناء السوء والمضلين في الدنيا",
      "ملخص_القسم": "يؤسس القسم للموقف العملي المطلوب من المؤمن في الدنيا تجاه من قد يضلونه، مؤكداً أن التبرؤ والبراءة منهم يجب أن يكون في الدنيا حيث ينفع، لا في الآخرة حيث لا فائدة منه.",
      "نطاق_الفقرات": {
        "البداية_sequence_index": 18,
        "النهاية_sequence_index": 36,
        "البداية_paragraph_id": "454de059-f9d1-4f60-b53f-1d07eb6d7f5f",
        "النهاية_paragraph_id": "1a480523-d4ce-4d98-af54-6ab72c77cab6"
      },
      "الآيات_المرتبطة": [
        {"رقم_الاية": "38", "اسم_السورة": "الزخرف"},
        {"رقم_الاية": "29", "اسم_السورة": "فصلت"}
      ],
      "concepts_tags": ["قرين السوء", "البراءة", "الموقف العملي", "الحذر", "الضلال", "الدنيا", "الآخرة"]
    },
    {
      "رقم_القسم": 3,
      "اسم_القسم": "أهمية البحث عن منابع الضلال ومكافحتها في الحياة الدنيا",
      "ملخص_القسم": "يُبرز القسم ضرورة المبادرة للتعرف على مصادر الضلال والمضلين في الدنيا والعمل على كشفهم ومواجهتهم، مستشهداً بآية طلب أهل النار رؤية من أضلهم كدليل على شدة الندم.",
      "نطاق_الفقرات": {
        "البداية_sequence_index": 37,
        "النهاية_sequence_index": 56,
        "البداية_paragraph_id": "cdf26eeb-95c1-483f-950e-5fe3ea86f130",
        "النهاية_paragraph_id": "23d0f84c-ed22-4a96-95f5-ed5020d3732e"
      },
      "الآيات_المرتبطة": [
        {"رقم_الاية": "29", "اسم_السورة": "فصلت"},
        {"رقم_الاية": "48", "اسم_السورة": "غافر"}
      ],
      "concepts_tags": ["منابع الضلال", "المواجهة", "الوهابية", "اليهود", "النصارى", "الوعي", "النشر"]
    },
    {
      "رقم_القسم": 4,
      "اسم_القسم": "واجب الإنقاذ والدعوة إلى الهدى كنموذج نبوي",
      "ملخص_القسم": "ينتقل القسم إلى الجانب الإيجابي المتمثل في واجب نشر الهدى وإنقاذ الآخرين من الضلال، مستلهماً من روحية النبي صلى الله عليه وآله في الحرص على هداية أمته.",
      "نطاق_الفقرات": {
        "البداية_sequence_index": 57,
        "النهاية_sequence_index": 76,
        "البداية_paragraph_id": "0c254beb-8d69-4ac7-9d7a-bb9fbe37c7d1",
        "النهاية_paragraph_id": "3f04dd37-458e-4cf0-ad09-01c00627f0fd"
      },
      "الآيات_المرتبطة": [
        {"رقم_الاية": "29", "اسم_السورة": "فصلت"},
        {"رقم_الاية": "3", "اسم_السورة": "الشعراء"},
        {"رقم_الاية": "75", "اسم_السورة": "النساء"}
      ],
      "concepts_tags": ["الدعوة", "الهداية", "الحرص النبوي", "إنقاذ الآخرين", "نشر الوعي", "المسئولية"]
    },
    {
      "رقم_القسم": 5,
      "اسم_القسم": "الاقتداء بالنبي في الاهتمام بالآخرين والعمل الجماعي",
      "ملخص_القسم": "يختتم الدرس بالتأكيد على أن الإيمان الحقيقي لا يقتصر على العلاقة الشخصية مع الله، بل يتجلى في الاهتمام بالآخرين والعمل الجماعي لهدايتهم، مستشهداً بآيات تصف حرص النبي على أمته.",
      "نطاق_الفقرات": {
        "البداية_sequence_index": 77,
        "النهاية_sequence_index": 89,
        "البداية_paragraph_id": "c87a3c81-e40b-4808-9b67-b7181df2c76b",
        "النهاية_paragraph_id": "a85d3190-e1af-4e67-844d-c17b4e004e19"
      },
      "الآيات_المرتبطة": [
        {"رقم_الاية": "3", "اسم_السورة": "الشعراء"},
        {"رقم_الاية": "75", "اسم_السورة": "النساء"},
        {"رقم_الاية": "128", "اسم_السورة": "التوبة"}
      ],
      "concepts_tags": ["الاقتداء النبوي", "العمل الجماعي", "الاهتمام بالأمة", "الإيمان العملي", "الجهاد", "الإنفاق"]
    }
  ]
}